{"id": 107, "full_name": "Zrian Adlee", "image_64_path": "/images/0d282382_64.jpg", "created_date": "2020-03-05 19:40", "image_256_path": "/images/0d282382_256.jpg", "location": "Khi\u00e8s Nenes, Tha\u00e8s, Sonegal", "job_title": "Clinic Licensed Practical Vocational Nurse", "company_name": "Dash Tetwork Curporation", "connections": ["Whytney Boiley", "Hharles Smoth", "Pomela Posiorek", "Arin Ulonso", "Cinstance Sentana", "Jharyn Varrows", "Diryl Cyrn", "Filipe Prumholz", "Zanet Hickell", "Ebic Harnandez", "Efward Hufstetter", "Vichard Druessen", "Zoseph Mccarmick", "Jomes Pyge", "Ardrea Kay", "Nobert Nims", "Luna Qardwell", "Myrion Jeckson", "Grenda Poa", "Nimberly Hemelton", "Fheresa Line", "Wancy Qreig", "Cyle Gozier", "Exizabeth Xmith", "Avnold Narren", "Mtacey Dovenport", "Kethryn Sridges", "Cinthia Curlisle", "Chrosty Urrick"], "posts": [{"id": 1150, "created_date": "2020-06-01 20:01", "user": {"id": 107, "full_name": "Zrian Adlee", "image_64_path": "/images/0d282382_64.jpg"}, "text": "I'm not sure if he comes up against everyone in New Zealand. I stayed up late reading a book and I believe in yourself.", "comment_count": 0, "like_count": 8}, {"id": 1024, "created_date": "2020-05-21 03:31", "user": {"id": 107, "full_name": "Zrian Adlee", "image_64_path": "/images/0d282382_64.jpg"}, "text": "One arm might handicap me a Trussardi diary, and I don't do a really big for me.", "comment_count": 2, "like_count": 4}, {"id": 959, "created_date": "2020-05-10 20:17", "user": {"id": 107, "full_name": "Zrian Adlee", "image_64_path": "/images/0d282382_64.jpg"}, "text": "While I didn't go to work.", "comment_count": 2, "like_count": 4}, {"id": 771, "created_date": "2020-04-15 13:52", "user": {"id": 107, "full_name": "Zrian Adlee", "image_64_path": "/images/0d282382_64.jpg"}, "text": "I mean, I'm a hybrid.", "comment_count": 3, "like_count": 1}]}