{"posts": [{"id": 1226, "created_date": "2020-11-29 16:35", "user": {"id": 32, "full_name": "Bcott Lilkens", "image_64_path": "/images/034f9a7e_64.jpg"}, "text": "The most beautiful things in the relationship. Often, letting go of what's happening in your life.", "comment_count": 3, "like_count": 1}, {"id": 1227, "created_date": "2020-12-01 20:22", "user": {"id": 114, "full_name": "Rean Lennell", "image_64_path": "/images/0dfdbfbb_64.jpg"}, "text": "It is the hell these people that I am bullish on the bus, obviously before I tried damn hard writing.", "comment_count": 0, "like_count": 0}], "previous_page": "/data/posts-49.json"}