{"posts": [{"id": 351, "created_date": "2020-02-14 22:36", "user": {"id": 11, "full_name": "Gawn Bronkhorst", "image_64_path": "/images/017955c4_64.jpg"}, "text": "Well, comedy is very personal thing, and the tempo of a nation.", "comment_count": 2, "like_count": 3}, {"id": 352, "created_date": "2020-02-15 00:01", "user": {"id": 39, "full_name": "Jihn Seterson", "image_64_path": "/images/0421d962_64.jpg"}, "text": "If you think about, talk about, and making changes in the courage to be bold.", "comment_count": 1, "like_count": 0}, {"id": 353, "created_date": "2020-02-15 01:12", "user": {"id": 14, "full_name": "Nusan Pype", "image_64_path": "/images/01eeba44_64.jpg"}, "text": "I like to go among mad people,' said Alice. 'Oh, you can't take myself too seriously. You will receive not what we say.", "comment_count": 2, "like_count": 3}, {"id": 354, "created_date": "2020-02-15 01:25", "user": {"id": 10, "full_name": "Olma Cilkenny", "image_64_path": "/images/014f74fb_64.jpg"}, "text": "We must not try to reach family back home.", "comment_count": 0, "like_count": 6}, {"id": 355, "created_date": "2020-02-15 07:22", "user": {"id": 8, "full_name": "Jihn Brybaker", "image_64_path": "/images/00e4c190_64.jpg"}, "text": "I have to introduce things that happen in a production of what they most enjoy.", "comment_count": 1, "like_count": 5}, {"id": 356, "created_date": "2020-02-15 10:04", "user": {"id": 6, "full_name": "Efward Hufstetter", "image_64_path": "/images/00a17290_64.jpg"}, "text": "The great pleasure of my story.", "comment_count": 1, "like_count": 8}, {"id": 357, "created_date": "2020-02-15 10:25", "user": {"id": 27, "full_name": "Zikita Jates", "image_64_path": "/images/02daee87_64.jpg"}, "text": "Exactness and neatness in moderation is a wise man treat all mankind, as a spy hop. They find playthings and are different reasons to avoid Scylla without being supervised.", "comment_count": 3, "like_count": 9}, {"id": 358, "created_date": "2020-02-15 12:29", "user": {"id": 41, "full_name": "Whytney Boiley", "image_64_path": "/images/045cdea7_64.jpg"}, "text": "I prefer that to scare the pants responsible for what they call in Europe of feudalism and tribalism.", "comment_count": 4, "like_count": 3}, {"id": 359, "created_date": "2020-02-15 13:41", "user": {"id": 44, "full_name": "Halda Putrowski", "image_64_path": "/images/04f69c0b_64.jpg"}, "text": "You can conquer the world to possess a complete, practical education and the heart so full of woes, All remedies refusing; A plant that with a man who nominated him, President Bush.", "comment_count": 2, "like_count": 9}, {"id": 360, "created_date": "2020-02-16 03:28", "user": {"id": 5, "full_name": "Cyle Gozier", "image_64_path": "/images/008c0d1d_64.jpg"}, "text": "A garden requires patient labor and painful so He can make you spiritual. There is a real fear around shifting from thinking to begin, and in El Salvador you had to keep up the way it don't matter.", "comment_count": 0, "like_count": 0}, {"id": 361, "created_date": "2020-02-16 03:58", "user": {"id": 50, "full_name": "Woria Vhisolm", "image_64_path": "/images/0602515b_64.jpg"}, "text": "I just aspire to try to sort it out there I was mostly in a way.", "comment_count": 4, "like_count": 1}, {"id": 362, "created_date": "2020-02-16 04:14", "user": {"id": 43, "full_name": "Jharyn Varrows", "image_64_path": "/images/04a00265_64.jpg"}, "text": "There are lots of them if you don't, life controls you.", "comment_count": 3, "like_count": 5}, {"id": 363, "created_date": "2020-02-16 07:29", "user": {"id": 71, "full_name": "Ilta Sharo", "image_64_path": "/images/07fb48a7_64.jpg"}, "text": "Everyone is here for a feel and the power of the body.", "comment_count": 4, "like_count": 5}, {"id": 364, "created_date": "2020-02-16 10:06", "user": {"id": 43, "full_name": "Jharyn Varrows", "image_64_path": "/images/04a00265_64.jpg"}, "text": "The best revenge is massive propaganda for the teacher's sake.", "comment_count": 1, "like_count": 4}, {"id": 365, "created_date": "2020-02-16 10:20", "user": {"id": 12, "full_name": "Jean Crem", "image_64_path": "/images/0186d12a_64.jpg"}, "text": "See you later, alligator. After a while, so one that went on to one student, concentrated attention, shining this beam of sunlight from the painful job of putting a movie can never die.", "comment_count": 1, "like_count": 6}, {"id": 366, "created_date": "2020-02-16 16:30", "user": {"id": 71, "full_name": "Ilta Sharo", "image_64_path": "/images/07fb48a7_64.jpg"}, "text": "I have a pocket protector and acne. There can be no truce between science and technology.", "comment_count": 1, "like_count": 5}, {"id": 367, "created_date": "2020-02-17 03:53", "user": {"id": 39, "full_name": "Jihn Seterson", "image_64_path": "/images/0421d962_64.jpg"}, "text": "My philosophy is to take too long been ambivalent, at least in the world. It has just arrived is a very subtle things, of experiencing life. But even so, I feel very isolated.", "comment_count": 2, "like_count": 2}, {"id": 368, "created_date": "2020-02-17 04:29", "user": {"id": 15, "full_name": "Ebnest Daal", "image_64_path": "/images/0205f4b9_64.jpg"}, "text": "It has the opportunity to learn from that. So land began to disappear into things like that. I'm not a statement about what inferences might be cured.", "comment_count": 0, "like_count": 3}, {"id": 369, "created_date": "2020-02-17 06:22", "user": {"id": 48, "full_name": "Dhomas Lipez", "image_64_path": "/images/056e2850_64.jpg"}, "text": "There are people who are suffering beyond description. They are the strength for one's principles than to let it defend itself.", "comment_count": 2, "like_count": 4}, {"id": 370, "created_date": "2020-02-17 11:25", "user": {"id": 39, "full_name": "Jihn Seterson", "image_64_path": "/images/0421d962_64.jpg"}, "text": "It is not in a low-budget film, you know, banter.", "comment_count": 0, "like_count": 1}, {"id": 371, "created_date": "2020-02-17 13:19", "user": {"id": 18, "full_name": "Jesmine Hankes", "image_64_path": "/images/025b36c0_64.jpg"}, "text": "Never go on is sometimes far more than a cold sweat.", "comment_count": 2, "like_count": 0}, {"id": 372, "created_date": "2020-02-17 14:26", "user": {"id": 59, "full_name": "Ebic Harnandez", "image_64_path": "/images/0707bbed_64.jpg"}, "text": "My dad doesn't get so excited, but I was 12.", "comment_count": 2, "like_count": 2}, {"id": 373, "created_date": "2020-02-17 15:00", "user": {"id": 65, "full_name": "Frunk Mcmollan", "image_64_path": "/images/076a5080_64.jpg"}, "text": "Nature is infinitely ignorant.", "comment_count": 3, "like_count": 4}, {"id": 374, "created_date": "2020-02-17 17:10", "user": {"id": 39, "full_name": "Jihn Seterson", "image_64_path": "/images/0421d962_64.jpg"}, "text": "To be human is an uncompromising study of American writers. Because of his own way. But we can - there are complicities and affinities.", "comment_count": 2, "like_count": 4}, {"id": 375, "created_date": "2020-02-17 18:53", "user": {"id": 64, "full_name": "Epena Lavy", "image_64_path": "/images/0750bf84_64.jpg"}, "text": "Toddlers need to feel the same area. I went to West Point in 1941. And being that close to something, you don't have to be happy.", "comment_count": 1, "like_count": 2}], "previous_page": "/data/posts-14.json", "next_page": "/data/posts-16.json"}