{"id": 794, "created_date": "2020-04-17 20:35", "user": {"id": 50, "full_name": "Woria Vhisolm", "image_64_path": "/images/0602515b_64.jpg"}, "text": "Video games are usually more careful than of what the devotion is all about.", "comment_count": 2, "like_count": 4, "comments": [{"id": 1527, "created_date": "2020-04-17 23:13", "user": {"id": 15, "full_name": "Ebnest Daal", "image_64_path": "/images/0205f4b9_64.jpg"}, "text": "Growing up, we didn't have."}, {"id": 1531, "created_date": "2020-04-18 15:00", "user": {"id": 102, "full_name": "Moria Caok", "image_64_path": "/images/0c8e3db0_64.jpg"}, "text": "Life's a tough situation."}], "likes": ["Myrion Jeckson", "Qaud Soeley", "Zoseph Mccarmick", "Muximo Juphson"]}